setup.py
potranslate/__init__.py
potranslate/__main__.py
potranslate.egg-info/PKG-INFO
potranslate.egg-info/SOURCES.txt
potranslate.egg-info/dependency_links.txt
potranslate.egg-info/entry_points.txt
potranslate.egg-info/requires.txt
potranslate.egg-info/top_level.txt