Metadata-Version: 1.0
Name: potranslate
Version: 0.1
Summary: PO File translation with GoogleTranslate
Home-page: https://github.com/bahattincinic/potranslate
Author: Bahattin Cinic
Author-email: bahattincinic@gmail.com
License: MIT
Platform: UNKNOWN
